tests/__init__.py
tests/test_unplate.py
unplate/__init__.py
unplate/compile.py
unplate/options.py
unplate/tokenize_util.py
unplate/util.py
unplate-0.2.8.dist-info/LICENSE
unplate-0.2.8.dist-info/METADATA
unplate-0.2.8.dist-info/WHEEL
unplate-0.2.8.dist-info/top_level.txt
unplate-0.2.8.dist-info/RECORD
