Metadata-Version: 2.1
Name: unplate
Version: 0.2.8
Summary: A templating language embedded into Python
Home-page: https://github.com/quelklef/unplate
Author: Quelklef
Author-email: 
License: UNKNOWN
Platform: UNKNOWN
Classifier: Programming Language :: Python :: 3
Classifier: License :: OSI Approved :: MIT License
Classifier: Operating System :: OS Independent
Requires-Python: >=3.6
